contexts/__init__.py
contexts/__main__.py
contexts/core.py
contexts/discovery.py
contexts/errors.py
contexts/plugin_discovery.py
contexts/plugin_interface.py
contexts/tools.py
contexts/plugins/__init__.py
contexts/plugins/argv_forwarder.py
contexts/plugins/shuffling.py
contexts/plugins/test_target_suppliers.py
contexts/plugins/identification/__init__.py
contexts/plugins/identification/decorators.py
contexts/plugins/identification/filespec.py
contexts/plugins/importing/__init__.py
contexts/plugins/importing/assertion_rewriting.py
contexts/plugins/reporting/__init__.py
contexts/plugins/reporting/cli.py
contexts/plugins/reporting/teamcity.py
contexts/plugins/reporting/xml.py
Contexts-0.11.2.dist-info/top_level.txt
Contexts-0.11.2.dist-info/entry_points.txt
Contexts-0.11.2.dist-info/METADATA
Contexts-0.11.2.dist-info/DESCRIPTION.rst
Contexts-0.11.2.dist-info/metadata.json
Contexts-0.11.2.dist-info/WHEEL
Contexts-0.11.2.dist-info/RECORD
